<?xml version="1.0" encoding="utf-8"?>
<ArrayOfTool xmlns:xsi="http://www.w3.org/2001/XMLSchema-instance" xmlns:xsd="http://www.w3.org/2001/XMLSchema">
  <Tool>
    <CategoryId>10</CategoryId>
    <ToolId>6</ToolId>
    <Manufactorer>SpeedTools</Manufactorer>
    <Bezeichnung>Rasenmaeher R900</Bezeichnung>
    <PowerSupply>Kabel</PowerSupply>
  </Tool>
  <Tool>
    <CategoryId>10</CategoryId>
    <ToolId>5</ToolId>
    <Manufactorer>Siemens</Manufactorer>
    <Description>Zauneidechse</Description>
    <PowerSupply>Akku</PowerSupply>
  </Tool>
  <Tool>
    <CategoryId>40</CategoryId>
    <ToolId>4</ToolId>
    <Manufactorer>Bleck&amp;Decker</Manufactorer>
    <Description>Bohrmaschine BD-98</Description>
    <PowerSupply>Kabel</PowerSupply>
  </Tool>
  <Tool>
    <CategoryId>20</CategoryId>
    <ToolId>3</ToolId>
    <Manufactorer>Bosch</Manufactorer>
    <Description>Handsäge GM-180z</Description>
    <PowerSupply>Akku</PowerSupply>
  </Tool>
  <Tool>
    <CategoryId>30</CategoryId>
    <ToolId>2</ToolId>
    <Manufactorer>Hilti</Manufactorer>
    <Description>Bohrhammer H190</Description>
    <PowerSupply>Stromlos</PowerSupply>
  </Tool>
</ArrayOfTool>